pypekit/__init__.py
pypekit/core.py
pypekit/hashing.py
pypekit-0.1.6.dist-info/METADATA
pypekit-0.1.6.dist-info/WHEEL
pypekit-0.1.6.dist-info/licenses/LICENSE
pypekit-0.1.6.dist-info/RECORD
